sagetasks/__init__.py
sagetasks/__main__.py
sagetasks/main.py
sagetasks/utils.py
sagetasks/nextflowtower/__init__.py
sagetasks/nextflowtower/client.py
sagetasks/nextflowtower/general.py
sagetasks/nextflowtower/typer.py
sagetasks/nextflowtower/utils.py
sagetasks/sevenbridges/__init__.py
sagetasks/sevenbridges/general.py
sagetasks/sevenbridges/inputs.py
sagetasks/sevenbridges/prefect.py
sagetasks/sevenbridges/utils.py
sagetasks/synapse/__init__.py
sagetasks/synapse/general.py
sagetasks/synapse/prefect.py
sagetasks-0.4.0.dist-info/LICENSE.txt
sagetasks-0.4.0.dist-info/METADATA
sagetasks-0.4.0.dist-info/WHEEL
sagetasks-0.4.0.dist-info/entry_points.txt
sagetasks-0.4.0.dist-info/top_level.txt
sagetasks-0.4.0.dist-info/RECORD
