Metadata-Version: 2.1
Name: sagetasks
Version: 0.4.0
Summary: Python library for building ETL pipelines involving Synapse and data processing workflows
Home-page: https://github.com/sage-Bionetworks-workflows/sagetasks
Author: Bruno Grande
Author-email: bruno.grande@sagebase.org
License: Apache-2.0
Project-URL: Source, https://github.com/sage-Bionetworks-workflows/sagetasks
Project-URL: Changelog, https://github.com/Sage-Bionetworks-Workflows/sagetasks/blob/main/CHANGELOG.md
Project-URL: Tracker, https://github.com/Sage-Bionetworks-Workflows/sagetasks/issues
Platform: any
Classifier: Development Status :: 4 - Beta
Classifier: Programming Language :: Python
Requires-Python: >=3.7
License-File: LICENSE.txt
Requires-Dist: prefect (>=2.0)
Requires-Dist: synapseclient
Requires-Dist: sevenbridges-python
Requires-Dist: pandas
Requires-Dist: typer
Requires-Dist: rich
Provides-Extra: dev
Requires-Dist: pre-commit ; extra == 'dev'
Requires-Dist: tox (==3.27.1) ; extra == 'dev'
Requires-Dist: sphinx-rtd-theme ; extra == 'dev'
Requires-Dist: black ; extra == 'dev'
Requires-Dist: isort ; extra == 'dev'
Requires-Dist: jupyterlab ; extra == 'dev'
Requires-Dist: mypy ; extra == 'dev'
Requires-Dist: types-requests ; extra == 'dev'
Provides-Extra: testing
Requires-Dist: setuptools ; extra == 'testing'
Requires-Dist: pytest ; extra == 'testing'
Requires-Dist: pytest-cov ; extra == 'testing'
Requires-Dist: pytest-mock ; extra == 'testing'
